[
  {
    "id": "4cbf8967-77dd-4029-a46b-77c794cf45ee",
    "timestamp": "2026-01-29T18:41:58.150Z",
    "action": "modify",
    "environmentName": "local",
    "fileName": ".env",
    "fileContent": "DB_HOST=aws-1-eu-west-1.pooler.supabase.com\r\nDB_PORT=5432\r\nDB_NAME=postgres\r\nDB_USERNAME=postgres.vdnhamzpvqtvqpirbefb\r\nDB_PASSWORD=ChaziziAirTracker",
    "diff": {
      "added": [],
      "removed": [],
      "changed": [],
      "unchanged": [
        {
          "key": "DB_HOST",
          "value": "aws-1-eu-west-1.pooler.supabase.com",
          "line": 1
        },
        {
          "key": "DB_PORT",
          "value": "5432",
          "line": 2
        },
        {
          "key": "DB_NAME",
          "value": "postgres",
          "line": 3
        },
        {
          "key": "DB_USERNAME",
          "value": "postgres.vdnhamzpvqtvqpirbefb",
          "line": 4
        },
        {
          "key": "DB_PASSWORD",
          "value": "ChaziziAirTracker",
          "line": 5
        }
      ]
    },
    "metadata": {
      "workspace": "c:\\Users\\CJohn\\Desktop\\java\\airticket",
      "source": "auto",
      "checksum": "f22bd160c672005b"
    }
  },
  {
    "id": "84f859c5-9aa3-4ad4-bc07-fae467bac7f6",
    "timestamp": "2026-01-29T18:40:57.760Z",
    "action": "modify",
    "environmentName": "local",
    "fileName": ".env",
    "fileContent": "DB_HOST=aws-1-eu-west-1.pooler.supabase.com\r\nDB_PORT=5432\r\nDB_NAME=postgres\r\nDB_USERNAME=postgres.vdnhamzpvqtvqpirbefb\r\nDB_PASSWORD=ChaziziAirTracker",
    "diff": {
      "added": [],
      "removed": [],
      "changed": [],
      "unchanged": [
        {
          "key": "DB_HOST",
          "value": "aws-1-eu-west-1.pooler.supabase.com",
          "line": 1
        },
        {
          "key": "DB_PORT",
          "value": "5432",
          "line": 2
        },
        {
          "key": "DB_NAME",
          "value": "postgres",
          "line": 3
        },
        {
          "key": "DB_USERNAME",
          "value": "postgres.vdnhamzpvqtvqpirbefb",
          "line": 4
        },
        {
          "key": "DB_PASSWORD",
          "value": "ChaziziAirTracker",
          "line": 5
        }
      ]
    },
    "metadata": {
      "workspace": "c:\\Users\\CJohn\\Desktop\\java\\airticket",
      "source": "auto",
      "checksum": "f22bd160c672005b"
    }
  },
  {
    "id": "e3981e56-0e6b-4284-ac0c-13805be932c4",
    "timestamp": "2026-01-29T18:40:46.418Z",
    "action": "modify",
    "environmentName": "local",
    "fileName": ".env",
    "fileContent": "DB_HOST=aws-1-eu-west-1.pooler.supabase.com\r\nDB_PORT=5432\r\nDB_NAME=postgres\r\nDB_USERNAME=postgres.vdnhamzpvqtvqpirbefb\r\nDB_PASSWORD=ChaziziAirTracker",
    "diff": {
      "added": [],
      "removed": [],
      "changed": [],
      "unchanged": [
        {
          "key": "DB_HOST",
          "value": "aws-1-eu-west-1.pooler.supabase.com",
          "line": 1
        },
        {
          "key": "DB_PORT",
          "value": "5432",
          "line": 2
        },
        {
          "key": "DB_NAME",
          "value": "postgres",
          "line": 3
        },
        {
          "key": "DB_USERNAME",
          "value": "postgres.vdnhamzpvqtvqpirbefb",
          "line": 4
        },
        {
          "key": "DB_PASSWORD",
          "value": "ChaziziAirTracker",
          "line": 5
        }
      ]
    },
    "metadata": {
      "workspace": "c:\\Users\\CJohn\\Desktop\\java\\airticket",
      "source": "auto",
      "checksum": "f22bd160c672005b"
    }
  },
  {
    "id": "914ade9d-1b90-489a-8af0-b50f349758ba",
    "timestamp": "2026-01-29T18:40:46.093Z",
    "action": "modify",
    "environmentName": "local",
    "fileName": ".env",
    "fileContent": "DB_HOST=aws-1-eu-west-1.pooler.supabase.com\r\nDB_PORT=5432\r\nDB_NAME=postgres\r\nDB_USERNAME=postgres.vdnhamzpvqtvqpirbefb\r\nDB_PASSWORD=ChaziziAirTracker",
    "diff": {
      "added": [],
      "removed": [],
      "changed": [],
      "unchanged": [
        {
          "key": "DB_HOST",
          "value": "aws-1-eu-west-1.pooler.supabase.com",
          "line": 1
        },
        {
          "key": "DB_PORT",
          "value": "5432",
          "line": 2
        },
        {
          "key": "DB_NAME",
          "value": "postgres",
          "line": 3
        },
        {
          "key": "DB_USERNAME",
          "value": "postgres.vdnhamzpvqtvqpirbefb",
          "line": 4
        },
        {
          "key": "DB_PASSWORD",
          "value": "ChaziziAirTracker",
          "line": 5
        }
      ]
    },
    "metadata": {
      "workspace": "c:\\Users\\CJohn\\Desktop\\java\\airticket",
      "source": "auto",
      "checksum": "f22bd160c672005b"
    }
  },
  {
    "id": "b6bc3ee4-59d3-4f5c-ae6c-25a0f80d0c0f",
    "timestamp": "2026-01-29T18:40:45.739Z",
    "action": "modify",
    "environmentName": "local",
    "fileName": ".env",
    "fileContent": "DB_HOST=aws-1-eu-west-1.pooler.supabase.com\r\nDB_PORT=5432\r\nDB_NAME=postgres\r\nDB_USERNAME=postgres.vdnhamzpvqtvqpirbefb\r\nDB_PASSWORD=ChaziziAirTracker",
    "diff": null,
    "metadata": {
      "workspace": "c:\\Users\\CJohn\\Desktop\\java\\airticket",
      "source": "auto",
      "checksum": "f22bd160c672005b"
    }
  }
]